yaml/__init__.py
yaml/composer.py
yaml/constructor.py
yaml/cyaml.py
yaml/dumper.py
yaml/emitter.py
yaml/error.py
yaml/events.py
yaml/loader.py
yaml/nodes.py
yaml/parser.py
yaml/reader.py
yaml/representer.py
yaml/resolver.py
yaml/scanner.py
yaml/serializer.py
yaml/tokens.py
yaml2/__init__.py
yaml2/composer.py
yaml2/constructor.py
yaml2/cyaml.py
yaml2/dumper.py
yaml2/emitter.py
yaml2/error.py
yaml2/events.py
yaml2/loader.py
yaml2/nodes.py
yaml2/parser.py
yaml2/reader.py
yaml2/representer.py
yaml2/resolver.py
yaml2/scanner.py
yaml2/serializer.py
yaml2/tokens.py
yaml2-0.0.1.dist-info/METADATA
yaml2-0.0.1.dist-info/WHEEL
yaml2-0.0.1.dist-info/top_level.txt
yaml2-0.0.1.dist-info/RECORD
