Metadata-Version: 1.1
Name: yaml2
Version: 0.0.1
Summary: Lobby bot.
Home-page: https://www.youtube.com/
Author: TCYT
Author-email: UNKNOWN
License: UNKNOWN
Platform: UNKNOWN
Classifier: Programming Language :: Python :: 3
Classifier: License :: OSI Approved :: MIT License
Classifier: Operating System :: OS Independent
